tbVectors
