Metadata-Version: 1.1
Name: tbVectors
Version: 0.0.3
Summary: An easy way to use vectors
Home-page: UNKNOWN
Author: Thomas Blume
Author-email: tblume10@yahoo.com
License: MIT
Keywords: vector
Platform: UNKNOWN
Classifier: Development Status :: 5 - Production/Stable
Classifier: Intended Audience :: Education
Classifier: Operating System :: Microsoft :: Windows :: Windows 10
Classifier: License :: OSI Approved :: MIT License
Classifier: Programming Language :: Python :: 3
